Workbook

Sheet Summary
A1: The TJX Companies, Inc. (TJX) - DCF valuation summary
A2: Built from SEC EDGAR XBRL filings (CIK 0000109198). Valuation date 2026-10-27. $ millions except per-share data. Every cell below is a formula linked to the model sheets.
A4: Value per share
A5: Current share price ($) | B5: ='Inputs'!$B$7
A6: DCF - Gordon growth ($) | B6: ='DCF'!$B$37
A7: upside / (downside) vs price | B7: ='Summary'!$B$6/'Summary'!$B$5-1
A8: DCF - exit multiple ($) | B8: ='DCF'!$C$37
A9: upside / (downside) vs price | B9: ='Summary'!$B$8/'Summary'!$B$5-1
A10: Trading comps - median peer EV/EBITDA ($) | B10: ='Comps'!$F$19
A11: Trading comps - median peer P/E ($) | B11: ='Comps'!$F$20
A12: 52-week range of closing prices ($) | B12: =TEXT('Inputs'!$B$9,"0.00")&" - "&TEXT('Inputs'!$B$10,"0.00")
A14: Key inputs
A15: WACC | B15: ='WACC'!$B$25
A16: Cost of equity | B16: ='WACC'!$B$7
A17: Beta (5y monthly vs S&P 500) | B17: ='Beta'!$H$4
A18: Risk-free rate | B18: ='Inputs'!$B$23
A19: Equity risk premium | B19: ='Inputs'!$B$24
A20: Terminal growth | B20: ='Inputs'!$B$25
A21: Exit EV/EBITDA (peer median) | B21: ='Comps'!$M$10
A22: Year-1 revenue growth | B22: ='Assumptions'!$B$5
A23: EBIT margin | B23: ='Assumptions'!$B$9
A24: Enterprise value (Gordon) | B24: ='DCF'!$B$31
A25: Terminal value share of EV (Gordon) | B25: ='DCF'!$B$40
A27: Sheets
A28: Inputs | B28: market data, balance sheet, rates, rating table (sources cited)
A29: Historicals | B29: 6 fiscal years from 10-K XBRL with derived ratios
A30: Beta | B30: 60 monthly returns and the SLOPE regression
A31: WACC | B31: CAPM cost of equity, synthetic-rating cost of debt, weights
A32: Comps | B32: peer EV/EBITDA and P/E; sets the exit multiple
A33: Assumptions | B33: every forecast driver, linked to its source
A34: DCF | B34: 5-year projection, discounting, both terminal values, equity bridge
A35: Sensitivity | B35: WACC x terminal growth and WACC x exit multiple grids
A36: Drivers | B36: one-at-a-time sensitivity (tornado) from the Python model

Sheet Inputs
A1: The TJX Companies, Inc. (TJX) - source data
A2: Blue = hard-coded input from the cited source. $ millions unless stated.
A3: Company and market data
A4: Company | B4: The TJX Companies, Inc. | C4: SEC CIK 0000109198
A5: Ticker | B5: TJX
A6: Valuation date (date of share price) | B6: 46322 | C6: Yahoo Finance daily close via yfinance
A7: Share price ($) | B7: 140.2 | C7: Yahoo Finance daily close via yfinance
A8: Shares outstanding (m) | B8: 1099.9741 | C8: 10-K/10-Q cover page, dei:EntityCommonStockSharesOutstanding as of 2026-08-21
A9: 52-week low close ($) | B9: 122.84 | C9: Yahoo Finance via yfinance
A10: 52-week high close ($) | B10: 168.41 | C10: Yahoo Finance via yfinance
A12: Latest balance sheet (2026-08-01, most recent 10-K or 10-Q)
A13: Balance sheet date | B13: 46235 | C13: SEC companyfacts
A14: Cash and equivalents | B14: 6004 | C14: CashAndCashEquivalentsAtCarryingValue
A15: Short-term investments | B15: 0 | C15: not reported (0)
A16: Debt - current portion | B16: 1000 | C16: LongTermDebtCurrent
A17: Short-term borrowings | B17: 0 | C17: not reported (0)
A18: Debt - non-current | B18: 1871 | C18: LongTermDebtNoncurrent
A19: Total debt | B19: ='Inputs'!$B$16+'Inputs'!$B$17+'Inputs'!$B$18 | C19: Operating lease liabilities excluded: lease cost is already inside EBIT
A20: Noncontrolling interest | B20: 0 | C20: not reported (0)
A22: Rates
A23: Risk-free rate (10-year Treasury) | B23: 0.05 | C23: FRED series DGS10 (10-Year Treasury Constant Maturity), 2026-10-26
A24: Equity risk premium | B24: 0.037 | C24: Damodaran (NYU Stern), implied ERP for the S&P 500, monthly update (ERPbymonth.xlsx, 'Last 12 months data'), 2026-10-01
A25: Terminal growth rate (choice) | B25: 0.025 | C25: Long-run nominal growth: ~2% inflation plus modest real growth; below the risk-free rate
A26: Last reported fiscal year end | B26: 46053 | C26: Latest 10-K
A28: Synthetic rating table (Damodaran, large non-financial firms, January 2026)
A29: Coverage from | B29: Coverage to | C29: Rating | D29: Default spread
A30: -100000 | B30: 0.199999 | C30: D2/D | D30: 0.19
A31: 0.2 | B31: 0.649999 | C31: C2/C | D31: 0.16
A32: 0.65 | B32: 0.799999 | C32: Ca2/CC | D32: 0.1261
A33: 0.8 | B33: 1.249999 | C33: Caa/CCC | D33: 0.0885
A34: 1.25 | B34: 1.499999 | C34: B3/B- | D34: 0.0509
A35: 1.5 | B35: 1.749999 | C35: B2/B | D35: 0.0321
A36: 1.75 | B36: 1.999999 | C36: B1/B+ | D36: 0.0275
A37: 2 | B37: 2.2499999 | C37: Ba2/BB | D37: 0.0184
A38: 2.25 | B38: 2.49999 | C38: Ba1/BB+ | D38: 0.0138
A39: 2.5 | B39: 2.999999 | C39: Baa2/BBB | D39: 0.0111
A40: 3 | B40: 4.249999 | C40: A3/A- | D40: 0.0089
A41: 4.25 | B41: 5.499999 | C41: A2/A | D41: 0.0078
... A44: 8.5 | B44: 100000 | C44: Aaa/AAA | D44: 0.004

Sheet Historicals
A1: The TJX Companies, Inc. - fiscal-year history from 10-K XBRL ($ millions)
A2: Fiscal year = calendar year in which the year ends. Blue = as reported in XBRL; black = formula.
A3: Line item | B3: FY2021 | C3: FY2022 | D3: FY2023 | E3: FY2024 | F3: FY2025 | G3: FY2026 | H3: Avg last 3 | I3: XBRL tag / definition
A4: Revenue | B4: 32137 | C4: 48550 | D4: 49936 | E4: 54217 | F4: 56360 | G4: 60372 | I4: RevenueFromContractWithCustomerIncludingAssessedTax
A5: Operating income (reported; 0 = not tagged) | B5: 0 | C5: 0 | D5: 0 | E5: 0 | F5: 0 | G5: 0 | I5: not reported
A6: Pre-tax income | B6: 89 | C6: 4398 | D6: 4636 | E6: 5967 | F6: 6483 | G6: 7299 | I6: IncomeLossFromContinuingOperationsBeforeIncomeTaxesExtraordinaryItemsNoncontrollingInterest
A7: Interest expense | B7: 199 | C7: 123 | D7: 91 | E7: 82 | F7: 78 | G7: 79 | I7: InterestExpense
A8: Interest income | B8: 13 | C8: 4 | D8: 78 | E8: 249 | F8: 257 | G8: 195 | I8: InvestmentIncomeInterest
A9: Depreciation & amortization | B9: 871 | C9: 868 | D9: 887 | E9: 964 | F9: 1104 | G9: 1247 | I9: DepreciationDepletionAndAmortization
A10: Income tax expense | B10: -1 | C10: 1115 | D10: 1138 | E10: 1493 | F10: 1619 | G10: 1805 | I10: IncomeTaxExpenseBenefit
A11: Capital expenditures | B11: 568 | C11: 1045 | D11: 1457 | E11: 1722 | F11: 1918 | G11: 1957 | I11: PaymentsToAcquirePropertyPlantAndEquipment
A12: Net income | B12: 90 | C12: 3283 | D12: 3498 | E12: 4474 | F12: 4864 | G12: 5494 | I12: NetIncomeLoss
A13: Diluted EPS ($) | B13: 0.07 | C13: 2.7 | D13: 2.97 | E13: 3.86 | F13: 4.26 | G13: 4.87 | I13: EarningsPerShareDiluted
A14: Diluted weighted shares (m) | B14: 1215 | C14: 1216 | D14: 1178 | E14: 1159 | F14: 1142 | G14: 1128 | I14: WeightedAverageNumberOfDilutedSharesOutstanding
A15: Total current assets | B15: 15739.337 | C15: 13259 | D15: 12456 | E15: 12664 | F15: 12991 | G15: 15202 | I15: AssetsCurrent
... A22: Total operating lease liabilities (memo, not in net debt) | B22: 9420.821 | C22: 9152.151 | D22: 9385 | E22: 9680 | F22: 9912 | G22: 10620 | I22: OperatingLeaseLiability
A24: Derived
A25: EBIT | B25: =IF(B5<>0,B5,B6+B7-B8) | C25: =IF(C5<>0,C5,C6+C7-C8) | D25: =IF(D5<>0,D5,D6+D7-D8) | E25: =IF(E5<>0,E5,E6+E7-E8) | F25: =IF(F5<>0,F5,F6+F7-F8) | G25: =IF(G5<>0,G5,G6+G7-G8) | I25: Reported operating income; if not tagged: pre-tax + interest expense - interest income
A26: EBITDA | B26: =B25+B9 | C26: =C25+C9 | D26: =D25+D9 | E26: =E25+E9 | F26: =F25+F9 | G26: =G25+G9
A27: Revenue growth | C27: =C4/B4-1 | D27: =D4/C4-1 | E27: =E4/D4-1 | F27: =F4/E4-1 | G27: =G4/F4-1
A28: EBIT margin | B28: =B25/B4 | C28: =C25/C4 | D28: =D25/D4 | E28: =E25/E4 | F28: =F25/F4 | G28: =G25/G4 | H28: =AVERAGE(E28:G28)
A29: Effective tax rate | B29: =B10/B6 | C29: =C10/C6 | D29: =D10/D6 | E29: =E10/E6 | F29: =F10/F6 | G29: =G10/G6 | H29: =AVERAGE(E29:G29)
A30: D&A % of revenue | B30: =B9/B4 | C30: =C9/C4 | D30: =D9/D4 | E30: =E9/E4 | F30: =F9/F4 | G30: =G9/G4 | H30: =AVERAGE(E30:G30)
A31: Capex % of revenue | B31: =B11/B4 | C31: =C11/C4 | D31: =D11/D4 | E31: =E11/E4 | F31: =F11/F4 | G31: =G11/G4 | H31: =AVERAGE(E31:G31)
A32: Net working capital (operating) | B32: =(B15-B16-B17)-(B18-B19-B20-B21) | C32: =(C15-C16-C17)-(C18-C19-C20-C21) | D32: =(D15-D16-D17)-(D18-D19-D20-D21) | E32: =(E15-E16-E17)-(E18-E19-E20-E21) | F32: =(F15-F16-F17)-(F18-F19-F20-F21) | G32: =(G15-G16-G17)-(G18-G19-G20-G21) | I32: (current assets - cash - ST investments) - (current liabilities - current debt - ST borrowings - current lease liabilities)
A33: NWC % of revenue | B33: =B32/B4 | C33: =C32/C4 | D33: =D32/D4 | E33: =E32/E4 | F33: =F32/F4 | G33: =G32/G4 | H33: =AVERAGE(E33:G33)
A34: Unlevered free cash flow (historical, for reference) | C34: =C25*(1-C29)+C9-C11-(C32-B32) | D34: =D25*(1-D29)+D9-D11-(D32-C32) | E34: =E25*(1-E29)+E9-E11-(E32-D32) | F34: =F25*(1-F29)+F9-F11-(F32-E32) | G34: =G25*(1-G29)+G9-G11-(G32-F32) | I34: EBIT x (1 - tax) + D&A - capex - change in NWC
A36: Note: The company does not tag an operating-income line for some years; EBIT is rebuilt as pre-tax income + interest expense - interest income.

Sheet Beta
A1: Beta: TJX vs S&P 500, monthly returns
A2: Adjusted month-end closes (Yahoo Finance via yfinance; index = ^GSPC). Beta = SLOPE of stock returns on index returns.
A4: Month | B4: TJX adj. close | C4: S&P 500 | D4: TJX return | E4: S&P 500 return | G4: Beta (SLOPE) | H4: =SLOPE(D6:D65,E6:E65)
A5: 44440 | B5: 61.376747 | C5: 4307.54 | G5: R-squared | H5: =RSQ(D6:D65,E6:E65)
A6: 44470 | B6: 60.920918 | C6: 4605.3799 | D6: =B6/B5-1 | E6: =C6/C5-1 | G6: Observations | H6: =COUNT(D6:D65)
A7: 44501 | B7: 64.799187 | C7: 4567 | D7: =B7/B6-1 | E7: =C7/C6-1 | G7: Blume-adjusted beta (0.67 x raw + 0.33), for reference only | H7: =0.67*H4+0.33
A8: 44531 | B8: 70.886955 | C8: 4766.1802 | D8: =B8/B7-1 | E8: =C8/C7-1
A9: 44562 | B9: 67.198814 | C9: 4515.5498 | D9: =B9/B8-1 | E9: =C9/C8-1
A10: 44593 | B10: 61.946617 | C10: 4373.9399 | D10: =B10/B9-1 | E10: =C10/C9-1
A11: 44621 | B11: 56.77346 | C11: 4530.4102 | D11: =B11/B10-1 | E11: =C11/C10-1
A12: 44652 | B12: 57.429482 | C12: 4131.9302 | D12: =B12/B11-1 | E12: =C12/C11-1
A13: 44682 | B13: 59.889961 | C13: 4132.1499 | D13: =B13/B12-1 | E13: =C13/C12-1
A14: 44713 | B14: 52.616863 | C14: 3785.3799 | D14: =B14/B13-1 | E14: =C14/C13-1
A15: 44743 | B15: 57.619473 | C15: 4130.29 | D15: =B15/B14-1 | E15: =C15/C14-1
A16: 44774 | B16: 59.018261 | C16: 3955 | D16: =B16/B15-1 | E16: =C16/C15-1
A17: 44805 | B17: 58.800545 | C17: 3585.6201 | D17: =B17/B16-1 | E17: =C17/C16-1
A18: 44835 | B18: 68.247246 | C18: 3871.98 | D18: =B18/B17-1 | E18: =C18/C17-1
A19: 44866 | B19: 76.086403 | C19: 4080.1101 | D19: =B19/B18-1 | E19: =C19/C18-1
... A65: 46266 | B65: 132.31 | C65: 7651.54 | D65: =B65/B64-1 | E65: =C65/C64-1

Sheet Comps
A1: Trading comparables (last fiscal year; prices as of the valuation date)
A2: EV = market cap + debt - cash - ST investments + NCI (latest 10-K/10-Q). EBITDA = EBIT + D&A and EPS = diluted EPS, both from the latest 10-K. $ millions.
A4: Ticker | B4: Company | C4: FY | D4: Price ($) | E4: Shares (m) | F4: Market cap | G4: Debt | H4: Cash + STI | I4: NCI | J4: Enterprise value | K4: EBITDA | L4: Diluted EPS ($) | M4: EV / EBITDA | N4: P / E
A5: ROST | B5: ROSS STORES, INC. | C5: FY2026 | D5: 230.09 | E5: 319.45311 | F5: =D5*E5 | G5: 1018.512 | H5: 4288.124 | I5: 0 | J5: =F5+G5-H5+I5 | K5: 3216.748 | L5: 6.61 | M5: =IF(K5>0,J5/K5,NA()) | N5: =IF(L5>0,D5/L5,NA())
A6: BURL | B6: Burlington Stores, Inc. | C6: FY2026 | D6: 235.15 | E6: 62.815195 | F6: =D6*E6 | G6: 1913.555 | H6: 703.686 | I6: 0 | J6: =F6+G6-H6+I6 | K6: 1284.126 | L6: 9.51 | M6: =IF(K6>0,J6/K6,NA()) | N6: =IF(L6>0,D6/L6,NA())
A7: OLLI | B7: Ollie's Bargain Outlet Holdings, Inc. | C7: FY2026 | D7: 84.72 | E7: 59.402403 | F7: =D7*E7 | G7: 2.229 | H7: 120.765 | I7: 0 | J7: =F7+G7-H7+I7 | K7: 352.865 | L7: 3.89 | M7: =IF(K7>0,J7/K7,NA()) | N7: =IF(L7>0,D7/L7,NA())
A8: TGT | B8: TARGET CORP | C8: FY2026 | D8: 148.01 | E8: 454.29674 | F8: =D8*E8 | G8: 15357 | H8: 5411 | I8: 0 | J8: =F8+G8-H8+I8 | K8: 8251 | L8: 8.13 | M8: =IF(K8>0,J8/K8,NA()) | N8: =IF(L8>0,D8/L8,NA())
A9: DG | B9: DOLLAR GENERAL CORP | C9: FY2026 | D9: 126.86 | E9: 220.61679 | F9: =D9*E9 | G9: 4570.815 | H9: 1589.59 | I9: 0 | J9: =F9+G9-H9+I9 | K9: 3249.986 | L9: 6.85 | M9: =IF(K9>0,J9/K9,NA()) | N9: =IF(L9>0,D9/L9,NA())
B10: Peer median | M10: =MEDIAN(M5:M9) | N10: =MEDIAN(N5:N9)
B11: Peer mean | M11: =AVERAGE(M5:M9) | N11: =AVERAGE(N5:N9)
B12: Peer min | M12: =MIN(M5:M9) | N12: =MIN(N5:N9)
B13: Peer max | M13: =MAX(M5:M9) | N13: =MAX(N5:N9)
A14: Target
A15: TJX | B15: The TJX Companies, Inc. | C15: FY2026 | D15: ='Inputs'!$B$7 | E15: ='Inputs'!$B$8 | F15: =D15*E15 | G15: ='Inputs'!$B$19 | H15: ='Inputs'!$B$14+'Inputs'!$B$15 | I15: ='Inputs'!$B$20 | J15: =F15+G15-H15+I15 | K15: ='Historicals'!$G$26 | L15: ='Historicals'!$G$13 | M15: =IF(K15>0,J15/K15,NA()) | N15: =IF(L15>0,D15/L15,NA())
A18: Implied value per share of target | E18: Low (peer min) | F18: Median | G18: High (peer max)
A19: From EV / EBITDA | E19: =(M12*K15-G15+H15-I15)/E15 | F19: =(M10*K15-G15+H15-I15)/E15 | G19: =(M13*K15-G15+H15-I15)/E15
A20: From P / E | E20: =N12*L15 | F20: =N10*L15 | G20: =N13*L15

Sheet WACC
A1: Weighted average cost of capital
A3: Cost of equity (CAPM)
A4: Risk-free rate | B4: ='Inputs'!$B$23 | C4: Inputs
A5: Levered beta (5y monthly regression) | B5: ='Beta'!$H$4 | C5: Beta sheet
A6: Equity risk premium | B6: ='Inputs'!$B$24 | C6: Inputs (Damodaran implied ERP)
A7: Cost of equity = Rf + Beta x ERP | B7: ='WACC'!$B$4+'WACC'!$B$5*'WACC'!$B$6
A9: Cost of debt (synthetic rating from interest coverage)
A10: EBIT, last fiscal year | B10: ='Historicals'!$G$25 | C10: Historicals
A11: Interest expense, last fiscal year | B11: ='Historicals'!$G$7 | C11: Historicals
A12: Interest coverage (EBIT / interest) | B12: =IF('WACC'!$B$11>0,'WACC'!$B$10/'WACC'!$B$11,100000)
A13: Synthetic rating | B13: =LOOKUP('WACC'!$B$12,'Inputs'!$A$30:$A$44,'Inputs'!$C$30:$C$44) | C13: Damodaran coverage table (Inputs)
A14: Default spread | B14: =LOOKUP('WACC'!$B$12,'Inputs'!$A$30:$A$44,'Inputs'!$D$30:$D$44)
A15: Pre-tax cost of debt = Rf + spread | B15: ='WACC'!$B$4+'WACC'!$B$14
A16: Tax rate (3-yr average effective) | B16: ='Historicals'!$H$29
A17: After-tax cost of debt | B17: ='WACC'!$B$15*(1-'WACC'!$B$16)
A19: Capital structure (market value of equity, book value of debt)
A20: Equity market value | B20: ='Inputs'!$B$7*'Inputs'!$B$8
A21: Debt | B21: ='Inputs'!$B$19
A22: Equity weight | B22: ='WACC'!$B$20/('WACC'!$B$20+'WACC'!$B$21)
A23: Debt weight | B23: ='WACC'!$B$21/('WACC'!$B$20+'WACC'!$B$21)
A25: WACC | B25: ='WACC'!$B$22*'WACC'!$B$7+'WACC'!$B$23*'WACC'!$B$17

Sheet Assumptions
A1: Forecast assumptions (each is a formula pointing at its source)
A3: Revenue
A4: Revenue CAGR, FY2023-FY2026 | B4: =('Historicals'!$G$4/'Historicals'!$D$4)^(1/3)-1 | C4: Historicals
A5: Year-1 revenue growth | B5: =MIN(MAX('Assumptions'!$B$4,-0.05),0.15) | C5: Historical CAGR, bounded to [-5%, 15%]
A6: Terminal growth | B6: ='Inputs'!$B$25 | C6: Inputs. Years 2-5 fade in a straight line from year-1 growth toward this rate
A7: Projection years | B7: 5
A8: Margins and reinvestment (3-year averages, FY2024-FY2026)
A9: EBIT margin | B9: ='Historicals'!$H$28 | C9: Historicals avg
A10: Tax rate | B10: ='Historicals'!$H$29 | C10: Historicals avg (effective rate)
A11: D&A % of revenue | B11: ='Historicals'!$H$30 | C11: Historicals avg
A12: Capex % of revenue | B12: ='Historicals'!$H$31 | C12: Historicals avg
A13: NWC % of revenue | B13: ='Historicals'!$H$33 | C13: Historicals avg; change in NWC = NWC% x change in revenue
A14: Discounting and terminal value
A15: WACC | B15: ='WACC'!$B$25 | C15: WACC sheet
A16: Exit EV/EBITDA multiple | B16: ='Comps'!$M$10 | C16: Peer median EV/EBITDA (Comps sheet)
A17: Cash-flow timing | B17: mid-year | C17: Year 1 counts only the part of the fiscal year after the valuation date; terminal value discounted from the end of year 5

Sheet DCF
A1: The TJX Companies, Inc. - unlevered DCF ($ millions)
B3: FY2026A | C3: FY2027E | D3: FY2028E | E3: FY2029E | F3: FY2030E | G3: FY2031E
A4: Year # | C4: 1 | D4: 2 | E4: 3 | F4: 4 | G4: 5
A5: Fiscal year end | B5: ='Inputs'!$B$26 | C5: =EDATE($B$5,12*C4) | D5: =EDATE($B$5,12*D4) | E5: =EDATE($B$5,12*E4) | F5: =EDATE($B$5,12*F4) | G5: =EDATE($B$5,12*G4)
A6: Revenue growth | C6: ='Assumptions'!$B$5+('Assumptions'!$B$6-'Assumptions'!$B$5)*(C4-1)/'Assumptions'!$B$7 | D6: ='Assumptions'!$B$5+('Assumptions'!$B$6-'Assumptions'!$B$5)*(D4-1)/'Assumptions'!$B$7 | E6: ='Assumptions'!$B$5+('Assumptions'!$B$6-'Assumptions'!$B$5)*(E4-1)/'Assumptions'!$B$7 | F6: ='Assumptions'!$B$5+('Assumptions'!$B$6-'Assumptions'!$B$5)*(F4-1)/'Assumptions'!$B$7 | G6: ='Assumptions'!$B$5+('Assumptions'!$B$6-'Assumptions'!$B$5)*(G4-1)/'Assumptions'!$B$7
A7: Revenue | B7: ='Historicals'!$G$4 | C7: =B7*(1+C6) | D7: =C7*(1+D6) | E7: =D7*(1+E6) | F7: =E7*(1+F6) | G7: =F7*(1+G6)
A8: EBIT margin | C8: ='Assumptions'!$B$9 | D8: ='Assumptions'!$B$9 | E8: ='Assumptions'!$B$9 | F8: ='Assumptions'!$B$9 | G8: ='Assumptions'!$B$9
A9: EBIT | C9: =C7*C8 | D9: =D7*D8 | E9: =E7*E8 | F9: =F7*F8 | G9: =G7*G8
A10: Tax rate | C10: ='Assumptions'!$B$10 | D10: ='Assumptions'!$B$10 | E10: ='Assumptions'!$B$10 | F10: ='Assumptions'!$B$10 | G10: ='Assumptions'!$B$10
A11: NOPAT = EBIT x (1 - tax) | C11: =C9*(1-C10) | D11: =D9*(1-D10) | E11: =E9*(1-E10) | F11: =F9*(1-F10) | G11: =G9*(1-G10)
A12: D&A % of revenue | C12: ='Assumptions'!$B$11 | D12: ='Assumptions'!$B$11 | E12: ='Assumptions'!$B$11 | F12: ='Assumptions'!$B$11 | G12: ='Assumptions'!$B$11
A13: Plus: D&A | C13: =C7*C12 | D13: =D7*D12 | E13: =E7*E12 | F13: =F7*F12 | G13: =G7*G12
A14: Capex % of revenue | C14: ='Assumptions'!$B$12 | D14: ='Assumptions'!$B$12 | E14: ='Assumptions'!$B$12 | F14: ='Assumptions'!$B$12 | G14: ='Assumptions'!$B$12
A15: Less: capex | C15: =C7*C14 | D15: =D7*D14 | E15: =E7*E14 | F15: =F7*F14 | G15: =G7*G14
A16: NWC % of revenue | C16: ='Assumptions'!$B$13 | D16: ='Assumptions'!$B$13 | E16: ='Assumptions'!$B$13 | F16: ='Assumptions'!$B$13 | G16: ='Assumptions'!$B$13
A17: Less: increase in NWC | C17: =C16*(C7-B7) | D17: =D16*(D7-C7) | E17: =E16*(E7-D7) | F17: =F16*(F7-E7) | G17: =G16*(G7-F7)
A18: Unlevered free cash flow | C18: =C11+C13-C15-C17 | D18: =D11+D13-D15-D17 | E18: =E11+E13-E15-E17 | F18: =F11+F13-F15-F17 | G18: =G11+G13-G15-G17
A19: EBITDA | C19: =C9+C13 | D19: =D9+D13 | E19: =E9+E13 | F19: =F9+F13 | G19: =G9+G13
A21: Share of year after valuation date | C21: =MAX(0,MIN(1,(C5-'Inputs'!$B$6)/365)) | D21: 1 | E21: 1 | F21: 1 | G21: 1
A22: Discount period (mid-year, years) | C22: =C21/2 | D22: =$C$21+(D4-1)-0.5 | E22: =$C$21+(E4-1)-0.5 | F22: =$C$21+(F4-1)-0.5 | G22: =$C$21+(G4-1)-0.5
A23: Discount factor | C23: =1/(1+'Assumptions'!$B$15)^C22 | D23: =1/(1+'Assumptions'!$B$15)^D22 | E23: =1/(1+'Assumptions'!$B$15)^E22 | F23: =1/(1+'Assumptions'!$B$15)^F22 | G23: =1/(1+'Assumptions'!$B$15)^G22
A24: PV of free cash flow | C24: =C18*C21*C23 | D24: =D18*D21*D23 | E24: =E18*E21*E23 | F24: =F18*F21*F23 | G24: =G18*G21*G23
A26: Valuation | B26: Gordon growth | C26: Exit multiple
A27: Sum of PV of free cash flows | B27: =SUM(C24:G24) | C27: =SUM(C24:G24)
A28: Terminal value (end of year 5) | B28: =G18*(1+'Assumptions'!$B$6)/('Assumptions'!$B$15-'Assumptions'!$B$6) | C28: =G19*'Assumptions'!$B$16
A29: Terminal value discount period (years) | B29: =$C$21+(G4-1) | C29: =$C$21+(G4-1)
A30: PV of terminal value | B30: =B28/(1+'Assumptions'!$B$15)^B29 | C30: =C28/(1+'Assumptions'!$B$15)^C29
A31: Enterprise value | B31: =B27+B30 | C31: =C27+C30
A32: Less: debt | B32: =-'Inputs'!$B$19 | C32: =-'Inputs'!$B$19
A33: Plus: cash and ST investments | B33: ='Inputs'!$B$14+'Inputs'!$B$15 | C33: ='Inputs'!$B$14+'Inputs'!$B$15
A34: Less: noncontrolling interest | B34: =-'Inputs'!$B$20 | C34: =-'Inputs'!$B$20
A35: Equity value | B35: =SUM(B31:B34) | C35: =SUM(C31:C34)
A36: Shares outstanding (m) | B36: ='Inputs'!$B$8 | C36: ='Inputs'!$B$8
A37: Implied value per share ($) | B37: =B35/B36 | C37: =C35/C36
A38: Current share price ($) | B38: ='Inputs'!$B$7 | C38: ='Inputs'!$B$7
A39: Upside / (downside) | B39: =B37/B38-1 | C39: =C37/C38-1
A40: PV of terminal value as % of EV | B40: =B30/B31 | C40: =C30/C31
A41: Cross-check: implied exit multiple / implied perpetual growth | B41: =B28/G19 | C41: =(C28*'Assumptions'!$B$15-G18)/(C28+G18)

Sheet Sensitivity
A1: Value per share sensitivity (live formulas; projected cash flows held fixed)
A3: Gordon growth: implied value per share ($)
A4: WACC (rows) vs terminal growth (columns)
B5: ='Inputs'!$B$25+(-0.01) | C5: ='Inputs'!$B$25+(-0.005) | D5: ='Inputs'!$B$25+(0.0) | E5: ='Inputs'!$B$25+(0.005) | F5: ='Inputs'!$B$25+(0.01)
A6: ='WACC'!$B$25+(-0.01) | B6: =IF($A6<=B$5,NA(),('DCF'!$C$18*'DCF'!$C$21/(1+$A6)^'DCF'!$C$22+'DCF'!$D$18*'DCF'!$D$21/(1+$A6)^'DCF'!$D$22+'DCF'!$E$18*'DCF'!$E$21/(1+$A6)^'DCF'!$E$22+'DCF'!$F$18*'DCF'!$F$21/(1+$A6)^'DCF'!$F$22+'DCF'!$G$18*'DCF'!$G$21/(1+$A6)^'DCF'!$G$22+'DCF'!$G$18*(1+B$5)/($A6-B$5)/(1+$A6)^'DCF'!$B$29-'Inputs'!$B$19+'Inputs'!$B$14+'Inputs'!$B$15-'Inputs'!$B$20)/'Inputs'!$B$8) | C6: =IF($A6<=C$5,NA(),('DCF'!$C$18*'DCF'!$C$21/(1+$A6)^'DCF'!$C$22+'DCF'!$D$18*'DCF'!$D$21/(1+$A6)^'DCF'!$D$22+'DCF'!$E$18*'DCF'!$E$21/(1+$A6)^'DCF'!$E$22+'DCF'!$F$18*'DCF'!$F$21/(1+$A6)^'DCF'!$F$22+'DCF'!$G$18*'DCF'!$G$21/(1+$A6)^'DCF'!$G$22+'DCF'!$G$18*(1+C$5)/($A6-C$5)/(1+$A6)^'DCF'!$B$29-'Inputs'!$B$19+'Inputs'!$B$14+'Inputs'!$B$15-'Inputs'!$B$20)/'Inputs'!$B$8) | D6: =IF($A6<=D$5,NA(),('DCF'!$C$18*'DCF'!$C$21/(1+$A6)^'DCF'!$C$22+'DCF'!$D$18*'DCF'!$D$21/(1+$A6)^'DCF'!$D$22+'DCF'!$E$18*'DCF'!$E$21/(1+$A6)^'DCF'!$E$22+'DCF'!$F$18*'DCF'!$F$21/(1+$A6)^'DCF'!$F$22+'DCF'!$G$18*'DCF'!$G$21/(1+$A6)^'DCF'!$G$22+'DCF'!$G$18*(1+D$5)/($A6-D$5)/(1+$A6)^'DCF'!$B$29-'Inputs'!$B$19+'Inputs'!$B$14+'Inputs'!$B$15-'Inputs'!$B$20)/'Inputs'!$B$8) | E6: =IF($A6<=E$5,NA(),('DCF'!$C$18*'DCF'!$C$21/(1+$A6)^'DCF'!$C$22+'DCF'!$D$18*'DCF'!$D$21/(1+$A6)^'DCF'!$D$22+'DCF'!$E$18*'DCF'!$E$21/(1+$A6)^'DCF'!$E$22+'DCF'!$F$18*'DCF'!$F$21/(1+$A6)^'DCF'!$F$22+'DCF'!$G$18*'DCF'!$G$21/(1+$A6)^'DCF'!$G$22+'DCF'!$G$18*(1+E$5)/($A6-E$5)/(1+$A6)^'DCF'!$B$29-'Inputs'!$B$19+'Inputs'!$B$14+'Inputs'!$B$15-'Inputs'!$B$20)/'Inputs'!$B$8) | F6: =IF($A6<=F$5,NA(),('DCF'!$C$18*'DCF'!$C$21/(1+$A6)^'DCF'!$C$22+'DCF'!$D$18*'DCF'!$D$21/(1+$A6)^'DCF'!$D$22+'DCF'!$E$18*'DCF'!$E$21/(1+$A6)^'DCF'!$E$22+'DCF'!$F$18*'DCF'!$F$21/(1+$A6)^'DCF'!$F$22+'DCF'!$G$18*'DCF'!$G$21/(1+$A6)^'DCF'!$G$22+'DCF'!$G$18*(1+F$5)/($A6-F$5)/(1+$A6)^'DCF'!$B$29-'Inputs'!$B$19+'Inputs'!$B$14+'Inputs'!$B$15-'Inputs'!$B$20)/'Inputs'!$B$8)
A7: ='WACC'!$B$25+(-0.005) | B7: =IF($A7<=B$5,NA(),('DCF'!$C$18*'DCF'!$C$21/(1+$A7)^'DCF'!$C$22+'DCF'!$D$18*'DCF'!$D$21/(1+$A7)^'DCF'!$D$22+'DCF'!$E$18*'DCF'!$E$21/(1+$A7)^'DCF'!$E$22+'DCF'!$F$18*'DCF'!$F$21/(1+$A7)^'DCF'!$F$22+'DCF'!$G$18*'DCF'!$G$21/(1+$A7)^'DCF'!$G$22+'DCF'!$G$18*(1+B$5)/($A7-B$5)/(1+$A7)^'DCF'!$B$29-'Inputs'!$B$19+'Inputs'!$B$14+'Inputs'!$B$15-'Inputs'!$B$20)/'Inputs'!$B$8) | C7: =IF($A7<=C$5,NA(),('DCF'!$C$18*'DCF'!$C$21/(1+$A7)^'DCF'!$C$22+'DCF'!$D$18*'DCF'!$D$21/(1+$A7)^'DCF'!$D$22+'DCF'!$E$18*'DCF'!$E$21/(1+$A7)^'DCF'!$E$22+'DCF'!$F$18*'DCF'!$F$21/(1+$A7)^'DCF'!$F$22+'DCF'!$G$18*'DCF'!$G$21/(1+$A7)^'DCF'!$G$22+'DCF'!$G$18*(1+C$5)/($A7-C$5)/(1+$A7)^'DCF'!$B$29-'Inputs'!$B$19+'Inputs'!$B$14+'Inputs'!$B$15-'Inputs'!$B$20)/'Inputs'!$B$8) | D7: =IF($A7<=D$5,NA(),('DCF'!$C$18*'DCF'!$C$21/(1+$A7)^'DCF'!$C$22+'DCF'!$D$18*'DCF'!$D$21/(1+$A7)^'DCF'!$D$22+'DCF'!$E$18*'DCF'!$E$21/(1+$A7)^'DCF'!$E$22+'DCF'!$F$18*'DCF'!$F$21/(1+$A7)^'DCF'!$F$22+'DCF'!$G$18*'DCF'!$G$21/(1+$A7)^'DCF'!$G$22+'DCF'!$G$18*(1+D$5)/($A7-D$5)/(1+$A7)^'DCF'!$B$29-'Inputs'!$B$19+'Inputs'!$B$14+'Inputs'!$B$15-'Inputs'!$B$20)/'Inputs'!$B$8) | E7: =IF($A7<=E$5,NA(),('DCF'!$C$18*'DCF'!$C$21/(1+$A7)^'DCF'!$C$22+'DCF'!$D$18*'DCF'!$D$21/(1+$A7)^'DCF'!$D$22+'DCF'!$E$18*'DCF'!$E$21/(1+$A7)^'DCF'!$E$22+'DCF'!$F$18*'DCF'!$F$21/(1+$A7)^'DCF'!$F$22+'DCF'!$G$18*'DCF'!$G$21/(1+$A7)^'DCF'!$G$22+'DCF'!$G$18*(1+E$5)/($A7-E$5)/(1+$A7)^'DCF'!$B$29-'Inputs'!$B$19+'Inputs'!$B$14+'Inputs'!$B$15-'Inputs'!$B$20)/'Inputs'!$B$8) | F7: =IF($A7<=F$5,NA(),('DCF'!$C$18*'DCF'!$C$21/(1+$A7)^'DCF'!$C$22+'DCF'!$D$18*'DCF'!$D$21/(1+$A7)^'DCF'!$D$22+'DCF'!$E$18*'DCF'!$E$21/(1+$A7)^'DCF'!$E$22+'DCF'!$F$18*'DCF'!$F$21/(1+$A7)^'DCF'!$F$22+'DCF'!$G$18*'DCF'!$G$21/(1+$A7)^'DCF'!$G$22+'DCF'!$G$18*(1+F$5)/($A7-F$5)/(1+$A7)^'DCF'!$B$29-'Inputs'!$B$19+'Inputs'!$B$14+'Inputs'!$B$15-'Inputs'!$B$20)/'Inputs'!$B$8)
A8: ='WACC'!$B$25+(0.0) | B8: =IF($A8<=B$5,NA(),('DCF'!$C$18*'DCF'!$C$21/(1+$A8)^'DCF'!$C$22+'DCF'!$D$18*'DCF'!$D$21/(1+$A8)^'DCF'!$D$22+'DCF'!$E$18*'DCF'!$E$21/(1+$A8)^'DCF'!$E$22+'DCF'!$F$18*'DCF'!$F$21/(1+$A8)^'DCF'!$F$22+'DCF'!$G$18*'DCF'!$G$21/(1+$A8)^'DCF'!$G$22+'DCF'!$G$18*(1+B$5)/($A8-B$5)/(1+$A8)^'DCF'!$B$29-'Inputs'!$B$19+'Inputs'!$B$14+'Inputs'!$B$15-'Inputs'!$B$20)/'Inputs'!$B$8) | C8: =IF($A8<=C$5,NA(),('DCF'!$C$18*'DCF'!$C$21/(1+$A8)^'DCF'!$C$22+'DCF'!$D$18*'DCF'!$D$21/(1+$A8)^'DCF'!$D$22+'DCF'!$E$18*'DCF'!$E$21/(1+$A8)^'DCF'!$E$22+'DCF'!$F$18*'DCF'!$F$21/(1+$A8)^'DCF'!$F$22+'DCF'!$G$18*'DCF'!$G$21/(1+$A8)^'DCF'!$G$22+'DCF'!$G$18*(1+C$5)/($A8-C$5)/(1+$A8)^'DCF'!$B$29-'Inputs'!$B$19+'Inputs'!$B$14+'Inputs'!$B$15-'Inputs'!$B$20)/'Inputs'!$B$8) | D8: =IF($A8<=D$5,NA(),('DCF'!$C$18*'DCF'!$C$21/(1+$A8)^'DCF'!$C$22+'DCF'!$D$18*'DCF'!$D$21/(1+$A8)^'DCF'!$D$22+'DCF'!$E$18*'DCF'!$E$21/(1+$A8)^'DCF'!$E$22+'DCF'!$F$18*'DCF'!$F$21/(1+$A8)^'DCF'!$F$22+'DCF'!$G$18*'DCF'!$G$21/(1+$A8)^'DCF'!$G$22+'DCF'!$G$18*(1+D$5)/($A8-D$5)/(1+$A8)^'DCF'!$B$29-'Inputs'!$B$19+'Inputs'!$B$14+'Inputs'!$B$15-'Inputs'!$B$20)/'Inputs'!$B$8) | E8: =IF($A8<=E$5,NA(),('DCF'!$C$18*'DCF'!$C$21/(1+$A8)^'DCF'!$C$22+'DCF'!$D$18*'DCF'!$D$21/(1+$A8)^'DCF'!$D$22+'DCF'!$E$18*'DCF'!$E$21/(1+$A8)^'DCF'!$E$22+'DCF'!$F$18*'DCF'!$F$21/(1+$A8)^'DCF'!$F$22+'DCF'!$G$18*'DCF'!$G$21/(1+$A8)^'DCF'!$G$22+'DCF'!$G$18*(1+E$5)/($A8-E$5)/(1+$A8)^'DCF'!$B$29-'Inputs'!$B$19+'Inputs'!$B$14+'Inputs'!$B$15-'Inputs'!$B$20)/'Inputs'!$B$8) | F8: =IF($A8<=F$5,NA(),('DCF'!$C$18*'DCF'!$C$21/(1+$A8)^'DCF'!$C$22+'DCF'!$D$18*'DCF'!$D$21/(1+$A8)^'DCF'!$D$22+'DCF'!$E$18*'DCF'!$E$21/(1+$A8)^'DCF'!$E$22+'DCF'!$F$18*'DCF'!$F$21/(1+$A8)^'DCF'!$F$22+'DCF'!$G$18*'DCF'!$G$21/(1+$A8)^'DCF'!$G$22+'DCF'!$G$18*(1+F$5)/($A8-F$5)/(1+$A8)^'DCF'!$B$29-'Inputs'!$B$19+'Inputs'!$B$14+'Inputs'!$B$15-'Inputs'!$B$20)/'Inputs'!$B$8)
A9: ='WACC'!$B$25+(0.005) | B9: =IF($A9<=B$5,NA(),('DCF'!$C$18*'DCF'!$C$21/(1+$A9)^'DCF'!$C$22+'DCF'!$D$18*'DCF'!$D$21/(1+$A9)^'DCF'!$D$22+'DCF'!$E$18*'DCF'!$E$21/(1+$A9)^'DCF'!$E$22+'DCF'!$F$18*'DCF'!$F$21/(1+$A9)^'DCF'!$F$22+'DCF'!$G$18*'DCF'!$G$21/(1+$A9)^'DCF'!$G$22+'DCF'!$G$18*(1+B$5)/($A9-B$5)/(1+$A9)^'DCF'!$B$29-'Inputs'!$B$19+'Inputs'!$B$14+'Inputs'!$B$15-'Inputs'!$B$20)/'Inputs'!$B$8) | C9: =IF($A9<=C$5,NA(),('DCF'!$C$18*'DCF'!$C$21/(1+$A9)^'DCF'!$C$22+'DCF'!$D$18*'DCF'!$D$21/(1+$A9)^'DCF'!$D$22+'DCF'!$E$18*'DCF'!$E$21/(1+$A9)^'DCF'!$E$22+'DCF'!$F$18*'DCF'!$F$21/(1+$A9)^'DCF'!$F$22+'DCF'!$G$18*'DCF'!$G$21/(1+$A9)^'DCF'!$G$22+'DCF'!$G$18*(1+C$5)/($A9-C$5)/(1+$A9)^'DCF'!$B$29-'Inputs'!$B$19+'Inputs'!$B$14+'Inputs'!$B$15-'Inputs'!$B$20)/'Inputs'!$B$8) | D9: =IF($A9<=D$5,NA(),('DCF'!$C$18*'DCF'!$C$21/(1+$A9)^'DCF'!$C$22+'DCF'!$D$18*'DCF'!$D$21/(1+$A9)^'DCF'!$D$22+'DCF'!$E$18*'DCF'!$E$21/(1+$A9)^'DCF'!$E$22+'DCF'!$F$18*'DCF'!$F$21/(1+$A9)^'DCF'!$F$22+'DCF'!$G$18*'DCF'!$G$21/(1+$A9)^'DCF'!$G$22+'DCF'!$G$18*(1+D$5)/($A9-D$5)/(1+$A9)^'DCF'!$B$29-'Inputs'!$B$19+'Inputs'!$B$14+'Inputs'!$B$15-'Inputs'!$B$20)/'Inputs'!$B$8) | E9: =IF($A9<=E$5,NA(),('DCF'!$C$18*'DCF'!$C$21/(1+$A9)^'DCF'!$C$22+'DCF'!$D$18*'DCF'!$D$21/(1+$A9)^'DCF'!$D$22+'DCF'!$E$18*'DCF'!$E$21/(1+$A9)^'DCF'!$E$22+'DCF'!$F$18*'DCF'!$F$21/(1+$A9)^'DCF'!$F$22+'DCF'!$G$18*'DCF'!$G$21/(1+$A9)^'DCF'!$G$22+'DCF'!$G$18*(1+E$5)/($A9-E$5)/(1+$A9)^'DCF'!$B$29-'Inputs'!$B$19+'Inputs'!$B$14+'Inputs'!$B$15-'Inputs'!$B$20)/'Inputs'!$B$8) | F9: =IF($A9<=F$5,NA(),('DCF'!$C$18*'DCF'!$C$21/(1+$A9)^'DCF'!$C$22+'DCF'!$D$18*'DCF'!$D$21/(1+$A9)^'DCF'!$D$22+'DCF'!$E$18*'DCF'!$E$21/(1+$A9)^'DCF'!$E$22+'DCF'!$F$18*'DCF'!$F$21/(1+$A9)^'DCF'!$F$22+'DCF'!$G$18*'DCF'!$G$21/(1+$A9)^'DCF'!$G$22+'DCF'!$G$18*(1+F$5)/($A9-F$5)/(1+$A9)^'DCF'!$B$29-'Inputs'!$B$19+'Inputs'!$B$14+'Inputs'!$B$15-'Inputs'!$B$20)/'Inputs'!$B$8)
A10: ='WACC'!$B$25+(0.01) | B10: =IF($A10<=B$5,NA(),('DCF'!$C$18*'DCF'!$C$21/(1+$A10)^'DCF'!$C$22+'DCF'!$D$18*'DCF'!$D$21/(1+$A10)^'DCF'!$D$22+'DCF'!$E$18*'DCF'!$E$21/(1+$A10)^'DCF'!$E$22+'DCF'!$F$18*'DCF'!$F$21/(1+$A10)^'DCF'!$F$22+'DCF'!$G$18*'DCF'!$G$21/(1+$A10)^'DCF'!$G$22+'DCF'!$G$18*(1+B$5)/($A10-B$5)/(1+$A10)^'DCF'!$B$29-'Inputs'!$B$19+'Inputs'!$B$14+'Inputs'!$B$15-'Inputs'!$B$20)/'Inputs'!$B$8) | C10: =IF($A10<=C$5,NA(),('DCF'!$C$18*'DCF'!$C$21/(1+$A10)^'DCF'!$C$22+'DCF'!$D$18*'DCF'!$D$21/(1+$A10)^'DCF'!$D$22+'DCF'!$E$18*'DCF'!$E$21/(1+$A10)^'DCF'!$E$22+'DCF'!$F$18*'DCF'!$F$21/(1+$A10)^'DCF'!$F$22+'DCF'!$G$18*'DCF'!$G$21/(1+$A10)^'DCF'!$G$22+'DCF'!$G$18*(1+C$5)/($A10-C$5)/(1+$A10)^'DCF'!$B$29-'Inputs'!$B$19+'Inputs'!$B$14+'Inputs'!$B$15-'Inputs'!$B$20)/'Inputs'!$B$8) | D10: =IF($A10<=D$5,NA(),('DCF'!$C$18*'DCF'!$C$21/(1+$A10)^'DCF'!$C$22+'DCF'!$D$18*'DCF'!$D$21/(1+$A10)^'DCF'!$D$22+'DCF'!$E$18*'DCF'!$E$21/(1+$A10)^'DCF'!$E$22+'DCF'!$F$18*'DCF'!$F$21/(1+$A10)^'DCF'!$F$22+'DCF'!$G$18*'DCF'!$G$21/(1+$A10)^'DCF'!$G$22+'DCF'!$G$18*(1+D$5)/($A10-D$5)/(1+$A10)^'DCF'!$B$29-'Inputs'!$B$19+'Inputs'!$B$14+'Inputs'!$B$15-'Inputs'!$B$20)/'Inputs'!$B$8) | E10: =IF($A10<=E$5,NA(),('DCF'!$C$18*'DCF'!$C$21/(1+$A10)^'DCF'!$C$22+'DCF'!$D$18*'DCF'!$D$21/(1+$A10)^'DCF'!$D$22+'DCF'!$E$18*'DCF'!$E$21/(1+$A10)^'DCF'!$E$22+'DCF'!$F$18*'DCF'!$F$21/(1+$A10)^'DCF'!$F$22+'DCF'!$G$18*'DCF'!$G$21/(1+$A10)^'DCF'!$G$22+'DCF'!$G$18*(1+E$5)/($A10-E$5)/(1+$A10)^'DCF'!$B$29-'Inputs'!$B$19+'Inputs'!$B$14+'Inputs'!$B$15-'Inputs'!$B$20)/'Inputs'!$B$8) | F10: =IF($A10<=F$5,NA(),('DCF'!$C$18*'DCF'!$C$21/(1+$A10)^'DCF'!$C$22+'DCF'!$D$18*'DCF'!$D$21/(1+$A10)^'DCF'!$D$22+'DCF'!$E$18*'DCF'!$E$21/(1+$A10)^'DCF'!$E$22+'DCF'!$F$18*'DCF'!$F$21/(1+$A10)^'DCF'!$F$22+'DCF'!$G$18*'DCF'!$G$21/(1+$A10)^'DCF'!$G$22+'DCF'!$G$18*(1+F$5)/($A10-F$5)/(1+$A10)^'DCF'!$B$29-'Inputs'!$B$19+'Inputs'!$B$14+'Inputs'!$B$15-'Inputs'!$B$20)/'Inputs'!$B$8)
A13: Exit multiple: implied value per share ($)
A14: WACC (rows) vs exit EV/EBITDA (columns)
B15: ='Comps'!$M$10+(-2) | C15: ='Comps'!$M$10+(-1) | D15: ='Comps'!$M$10+(0) | E15: ='Comps'!$M$10+(1) | F15: ='Comps'!$M$10+(2)
A16: ='WACC'!$B$25+(-0.01) | B16: =('DCF'!$C$18*'DCF'!$C$21/(1+$A16)^'DCF'!$C$22+'DCF'!$D$18*'DCF'!$D$21/(1+$A16)^'DCF'!$D$22+'DCF'!$E$18*'DCF'!$E$21/(1+$A16)^'DCF'!$E$22+'DCF'!$F$18*'DCF'!$F$21/(1+$A16)^'DCF'!$F$22+'DCF'!$G$18*'DCF'!$G$21/(1+$A16)^'DCF'!$G$22+'DCF'!$G$19*B$15/(1+$A16)^'DCF'!$B$29-'Inputs'!$B$19+'Inputs'!$B$14+'Inputs'!$B$15-'Inputs'!$B$20)/'Inputs'!$B$8 | C16: =('DCF'!$C$18*'DCF'!$C$21/(1+$A16)^'DCF'!$C$22+'DCF'!$D$18*'DCF'!$D$21/(1+$A16)^'DCF'!$D$22+'DCF'!$E$18*'DCF'!$E$21/(1+$A16)^'DCF'!$E$22+'DCF'!$F$18*'DCF'!$F$21/(1+$A16)^'DCF'!$F$22+'DCF'!$G$18*'DCF'!$G$21/(1+$A16)^'DCF'!$G$22+'DCF'!$G$19*C$15/(1+$A16)^'DCF'!$B$29-'Inputs'!$B$19+'Inputs'!$B$14+'Inputs'!$B$15-'Inputs'!$B$20)/'Inputs'!$B$8 | D16: =('DCF'!$C$18*'DCF'!$C$21/(1+$A16)^'DCF'!$C$22+'DCF'!$D$18*'DCF'!$D$21/(1+$A16)^'DCF'!$D$22+'DCF'!$E$18*'DCF'!$E$21/(1+$A16)^'DCF'!$E$22+'DCF'!$F$18*'DCF'!$F$21/(1+$A16)^'DCF'!$F$22+'DCF'!$G$18*'DCF'!$G$21/(1+$A16)^'DCF'!$G$22+'DCF'!$G$19*D$15/(1+$A16)^'DCF'!$B$29-'Inputs'!$B$19+'Inputs'!$B$14+'Inputs'!$B$15-'Inputs'!$B$20)/'Inputs'!$B$8 | E16: =('DCF'!$C$18*'DCF'!$C$21/(1+$A16)^'DCF'!$C$22+'DCF'!$D$18*'DCF'!$D$21/(1+$A16)^'DCF'!$D$22+'DCF'!$E$18*'DCF'!$E$21/(1+$A16)^'DCF'!$E$22+'DCF'!$F$18*'DCF'!$F$21/(1+$A16)^'DCF'!$F$22+'DCF'!$G$18*'DCF'!$G$21/(1+$A16)^'DCF'!$G$22+'DCF'!$G$19*E$15/(1+$A16)^'DCF'!$B$29-'Inputs'!$B$19+'Inputs'!$B$14+'Inputs'!$B$15-'Inputs'!$B$20)/'Inputs'!$B$8 | F16: =('DCF'!$C$18*'DCF'!$C$21/(1+$A16)^'DCF'!$C$22+'DCF'!$D$18*'DCF'!$D$21/(1+$A16)^'DCF'!$D$22+'DCF'!$E$18*'DCF'!$E$21/(1+$A16)^'DCF'!$E$22+'DCF'!$F$18*'DCF'!$F$21/(1+$A16)^'DCF'!$F$22+'DCF'!$G$18*'DCF'!$G$21/(1+$A16)^'DCF'!$G$22+'DCF'!$G$19*F$15/(1+$A16)^'DCF'!$B$29-'Inputs'!$B$19+'Inputs'!$B$14+'Inputs'!$B$15-'Inputs'!$B$20)/'Inputs'!$B$8
A17: ='WACC'!$B$25+(-0.005) | B17: =('DCF'!$C$18*'DCF'!$C$21/(1+$A17)^'DCF'!$C$22+'DCF'!$D$18*'DCF'!$D$21/(1+$A17)^'DCF'!$D$22+'DCF'!$E$18*'DCF'!$E$21/(1+$A17)^'DCF'!$E$22+'DCF'!$F$18*'DCF'!$F$21/(1+$A17)^'DCF'!$F$22+'DCF'!$G$18*'DCF'!$G$21/(1+$A17)^'DCF'!$G$22+'DCF'!$G$19*B$15/(1+$A17)^'DCF'!$B$29-'Inputs'!$B$19+'Inputs'!$B$14+'Inputs'!$B$15-'Inputs'!$B$20)/'Inputs'!$B$8 | C17: =('DCF'!$C$18*'DCF'!$C$21/(1+$A17)^'DCF'!$C$22+'DCF'!$D$18*'DCF'!$D$21/(1+$A17)^'DCF'!$D$22+'DCF'!$E$18*'DCF'!$E$21/(1+$A17)^'DCF'!$E$22+'DCF'!$F$18*'DCF'!$F$21/(1+$A17)^'DCF'!$F$22+'DCF'!$G$18*'DCF'!$G$21/(1+$A17)^'DCF'!$G$22+'DCF'!$G$19*C$15/(1+$A17)^'DCF'!$B$29-'Inputs'!$B$19+'Inputs'!$B$14+'Inputs'!$B$15-'Inputs'!$B$20)/'Inputs'!$B$8 | D17: =('DCF'!$C$18*'DCF'!$C$21/(1+$A17)^'DCF'!$C$22+'DCF'!$D$18*'DCF'!$D$21/(1+$A17)^'DCF'!$D$22+'DCF'!$E$18*'DCF'!$E$21/(1+$A17)^'DCF'!$E$22+'DCF'!$F$18*'DCF'!$F$21/(1+$A17)^'DCF'!$F$22+'DCF'!$G$18*'DCF'!$G$21/(1+$A17)^'DCF'!$G$22+'DCF'!$G$19*D$15/(1+$A17)^'DCF'!$B$29-'Inputs'!$B$19+'Inputs'!$B$14+'Inputs'!$B$15-'Inputs'!$B$20)/'Inputs'!$B$8 | E17: =('DCF'!$C$18*'DCF'!$C$21/(1+$A17)^'DCF'!$C$22+'DCF'!$D$18*'DCF'!$D$21/(1+$A17)^'DCF'!$D$22+'DCF'!$E$18*'DCF'!$E$21/(1+$A17)^'DCF'!$E$22+'DCF'!$F$18*'DCF'!$F$21/(1+$A17)^'DCF'!$F$22+'DCF'!$G$18*'DCF'!$G$21/(1+$A17)^'DCF'!$G$22+'DCF'!$G$19*E$15/(1+$A17)^'DCF'!$B$29-'Inputs'!$B$19+'Inputs'!$B$14+'Inputs'!$B$15-'Inputs'!$B$20)/'Inputs'!$B$8 | F17: =('DCF'!$C$18*'DCF'!$C$21/(1+$A17)^'DCF'!$C$22+'DCF'!$D$18*'DCF'!$D$21/(1+$A17)^'DCF'!$D$22+'DCF'!$E$18*'DCF'!$E$21/(1+$A17)^'DCF'!$E$22+'DCF'!$F$18*'DCF'!$F$21/(1+$A17)^'DCF'!$F$22+'DCF'!$G$18*'DCF'!$G$21/(1+$A17)^'DCF'!$G$22+'DCF'!$G$19*F$15/(1+$A17)^'DCF'!$B$29-'Inputs'!$B$19+'Inputs'!$B$14+'Inputs'!$B$15-'Inputs'!$B$20)/'Inputs'!$B$8
A18: ='WACC'!$B$25+(0.0) | B18: =('DCF'!$C$18*'DCF'!$C$21/(1+$A18)^'DCF'!$C$22+'DCF'!$D$18*'DCF'!$D$21/(1+$A18)^'DCF'!$D$22+'DCF'!$E$18*'DCF'!$E$21/(1+$A18)^'DCF'!$E$22+'DCF'!$F$18*'DCF'!$F$21/(1+$A18)^'DCF'!$F$22+'DCF'!$G$18*'DCF'!$G$21/(1+$A18)^'DCF'!$G$22+'DCF'!$G$19*B$15/(1+$A18)^'DCF'!$B$29-'Inputs'!$B$19+'Inputs'!$B$14+'Inputs'!$B$15-'Inputs'!$B$20)/'Inputs'!$B$8 | C18: =('DCF'!$C$18*'DCF'!$C$21/(1+$A18)^'DCF'!$C$22+'DCF'!$D$18*'DCF'!$D$21/(1+$A18)^'DCF'!$D$22+'DCF'!$E$18*'DCF'!$E$21/(1+$A18)^'DCF'!$E$22+'DCF'!$F$18*'DCF'!$F$21/(1+$A18)^'DCF'!$F$22+'DCF'!$G$18*'DCF'!$G$21/(1+$A18)^'DCF'!$G$22+'DCF'!$G$19*C$15/(1+$A18)^'DCF'!$B$29-'Inputs'!$B$19+'Inputs'!$B$14+'Inputs'!$B$15-'Inputs'!$B$20)/'Inputs'!$B$8 | D18: =('DCF'!$C$18*'DCF'!$C$21/(1+$A18)^'DCF'!$C$22+'DCF'!$D$18*'DCF'!$D$21/(1+$A18)^'DCF'!$D$22+'DCF'!$E$18*'DCF'!$E$21/(1+$A18)^'DCF'!$E$22+'DCF'!$F$18*'DCF'!$F$21/(1+$A18)^'DCF'!$F$22+'DCF'!$G$18*'DCF'!$G$21/(1+$A18)^'DCF'!$G$22+'DCF'!$G$19*D$15/(1+$A18)^'DCF'!$B$29-'Inputs'!$B$19+'Inputs'!$B$14+'Inputs'!$B$15-'Inputs'!$B$20)/'Inputs'!$B$8 | E18: =('DCF'!$C$18*'DCF'!$C$21/(1+$A18)^'DCF'!$C$22+'DCF'!$D$18*'DCF'!$D$21/(1+$A18)^'DCF'!$D$22+'DCF'!$E$18*'DCF'!$E$21/(1+$A18)^'DCF'!$E$22+'DCF'!$F$18*'DCF'!$F$21/(1+$A18)^'DCF'!$F$22+'DCF'!$G$18*'DCF'!$G$21/(1+$A18)^'DCF'!$G$22+'DCF'!$G$19*E$15/(1+$A18)^'DCF'!$B$29-'Inputs'!$B$19+'Inputs'!$B$14+'Inputs'!$B$15-'Inputs'!$B$20)/'Inputs'!$B$8 | F18: =('DCF'!$C$18*'DCF'!$C$21/(1+$A18)^'DCF'!$C$22+'DCF'!$D$18*'DCF'!$D$21/(1+$A18)^'DCF'!$D$22+'DCF'!$E$18*'DCF'!$E$21/(1+$A18)^'DCF'!$E$22+'DCF'!$F$18*'DCF'!$F$21/(1+$A18)^'DCF'!$F$22+'DCF'!$G$18*'DCF'!$G$21/(1+$A18)^'DCF'!$G$22+'DCF'!$G$19*F$15/(1+$A18)^'DCF'!$B$29-'Inputs'!$B$19+'Inputs'!$B$14+'Inputs'!$B$15-'Inputs'!$B$20)/'Inputs'!$B$8
A19: ='WACC'!$B$25+(0.005) | B19: =('DCF'!$C$18*'DCF'!$C$21/(1+$A19)^'DCF'!$C$22+'DCF'!$D$18*'DCF'!$D$21/(1+$A19)^'DCF'!$D$22+'DCF'!$E$18*'DCF'!$E$21/(1+$A19)^'DCF'!$E$22+'DCF'!$F$18*'DCF'!$F$21/(1+$A19)^'DCF'!$F$22+'DCF'!$G$18*'DCF'!$G$21/(1+$A19)^'DCF'!$G$22+'DCF'!$G$19*B$15/(1+$A19)^'DCF'!$B$29-'Inputs'!$B$19+'Inputs'!$B$14+'Inputs'!$B$15-'Inputs'!$B$20)/'Inputs'!$B$8 | C19: =('DCF'!$C$18*'DCF'!$C$21/(1+$A19)^'DCF'!$C$22+'DCF'!$D$18*'DCF'!$D$21/(1+$A19)^'DCF'!$D$22+'DCF'!$E$18*'DCF'!$E$21/(1+$A19)^'DCF'!$E$22+'DCF'!$F$18*'DCF'!$F$21/(1+$A19)^'DCF'!$F$22+'DCF'!$G$18*'DCF'!$G$21/(1+$A19)^'DCF'!$G$22+'DCF'!$G$19*C$15/(1+$A19)^'DCF'!$B$29-'Inputs'!$B$19+'Inputs'!$B$14+'Inputs'!$B$15-'Inputs'!$B$20)/'Inputs'!$B$8 | D19: =('DCF'!$C$18*'DCF'!$C$21/(1+$A19)^'DCF'!$C$22+'DCF'!$D$18*'DCF'!$D$21/(1+$A19)^'DCF'!$D$22+'DCF'!$E$18*'DCF'!$E$21/(1+$A19)^'DCF'!$E$22+'DCF'!$F$18*'DCF'!$F$21/(1+$A19)^'DCF'!$F$22+'DCF'!$G$18*'DCF'!$G$21/(1+$A19)^'DCF'!$G$22+'DCF'!$G$19*D$15/(1+$A19)^'DCF'!$B$29-'Inputs'!$B$19+'Inputs'!$B$14+'Inputs'!$B$15-'Inputs'!$B$20)/'Inputs'!$B$8 | E19: =('DCF'!$C$18*'DCF'!$C$21/(1+$A19)^'DCF'!$C$22+'DCF'!$D$18*'DCF'!$D$21/(1+$A19)^'DCF'!$D$22+'DCF'!$E$18*'DCF'!$E$21/(1+$A19)^'DCF'!$E$22+'DCF'!$F$18*'DCF'!$F$21/(1+$A19)^'DCF'!$F$22+'DCF'!$G$18*'DCF'!$G$21/(1+$A19)^'DCF'!$G$22+'DCF'!$G$19*E$15/(1+$A19)^'DCF'!$B$29-'Inputs'!$B$19+'Inputs'!$B$14+'Inputs'!$B$15-'Inputs'!$B$20)/'Inputs'!$B$8 | F19: =('DCF'!$C$18*'DCF'!$C$21/(1+$A19)^'DCF'!$C$22+'DCF'!$D$18*'DCF'!$D$21/(1+$A19)^'DCF'!$D$22+'DCF'!$E$18*'DCF'!$E$21/(1+$A19)^'DCF'!$E$22+'DCF'!$F$18*'DCF'!$F$21/(1+$A19)^'DCF'!$F$22+'DCF'!$G$18*'DCF'!$G$21/(1+$A19)^'DCF'!$G$22+'DCF'!$G$19*F$15/(1+$A19)^'DCF'!$B$29-'Inputs'!$B$19+'Inputs'!$B$14+'Inputs'!$B$15-'Inputs'!$B$20)/'Inputs'!$B$8
A20: ='WACC'!$B$25+(0.01) | B20: =('DCF'!$C$18*'DCF'!$C$21/(1+$A20)^'DCF'!$C$22+'DCF'!$D$18*'DCF'!$D$21/(1+$A20)^'DCF'!$D$22+'DCF'!$E$18*'DCF'!$E$21/(1+$A20)^'DCF'!$E$22+'DCF'!$F$18*'DCF'!$F$21/(1+$A20)^'DCF'!$F$22+'DCF'!$G$18*'DCF'!$G$21/(1+$A20)^'DCF'!$G$22+'DCF'!$G$19*B$15/(1+$A20)^'DCF'!$B$29-'Inputs'!$B$19+'Inputs'!$B$14+'Inputs'!$B$15-'Inputs'!$B$20)/'Inputs'!$B$8 | C20: =('DCF'!$C$18*'DCF'!$C$21/(1+$A20)^'DCF'!$C$22+'DCF'!$D$18*'DCF'!$D$21/(1+$A20)^'DCF'!$D$22+'DCF'!$E$18*'DCF'!$E$21/(1+$A20)^'DCF'!$E$22+'DCF'!$F$18*'DCF'!$F$21/(1+$A20)^'DCF'!$F$22+'DCF'!$G$18*'DCF'!$G$21/(1+$A20)^'DCF'!$G$22+'DCF'!$G$19*C$15/(1+$A20)^'DCF'!$B$29-'Inputs'!$B$19+'Inputs'!$B$14+'Inputs'!$B$15-'Inputs'!$B$20)/'Inputs'!$B$8 | D20: =('DCF'!$C$18*'DCF'!$C$21/(1+$A20)^'DCF'!$C$22+'DCF'!$D$18*'DCF'!$D$21/(1+$A20)^'DCF'!$D$22+'DCF'!$E$18*'DCF'!$E$21/(1+$A20)^'DCF'!$E$22+'DCF'!$F$18*'DCF'!$F$21/(1+$A20)^'DCF'!$F$22+'DCF'!$G$18*'DCF'!$G$21/(1+$A20)^'DCF'!$G$22+'DCF'!$G$19*D$15/(1+$A20)^'DCF'!$B$29-'Inputs'!$B$19+'Inputs'!$B$14+'Inputs'!$B$15-'Inputs'!$B$20)/'Inputs'!$B$8 | E20: =('DCF'!$C$18*'DCF'!$C$21/(1+$A20)^'DCF'!$C$22+'DCF'!$D$18*'DCF'!$D$21/(1+$A20)^'DCF'!$D$22+'DCF'!$E$18*'DCF'!$E$21/(1+$A20)^'DCF'!$E$22+'DCF'!$F$18*'DCF'!$F$21/(1+$A20)^'DCF'!$F$22+'DCF'!$G$18*'DCF'!$G$21/(1+$A20)^'DCF'!$G$22+'DCF'!$G$19*E$15/(1+$A20)^'DCF'!$B$29-'Inputs'!$B$19+'Inputs'!$B$14+'Inputs'!$B$15-'Inputs'!$B$20)/'Inputs'!$B$8 | F20: =('DCF'!$C$18*'DCF'!$C$21/(1+$A20)^'DCF'!$C$22+'DCF'!$D$18*'DCF'!$D$21/(1+$A20)^'DCF'!$D$22+'DCF'!$E$18*'DCF'!$E$21/(1+$A20)^'DCF'!$E$22+'DCF'!$F$18*'DCF'!$F$21/(1+$A20)^'DCF'!$F$22+'DCF'!$G$18*'DCF'!$G$21/(1+$A20)^'DCF'!$G$22+'DCF'!$G$19*F$15/(1+$A20)^'DCF'!$B$29-'Inputs'!$B$19+'Inputs'!$B$14+'Inputs'!$B$15-'Inputs'!$B$20)/'Inputs'!$B$8
A22: Green text = at or above the current share price.

Sheet Drivers
A1: What moves the answer most (one input moved at a time, full model re-run)
A2: Values computed by the Python model (dcf/core.py: tornado) and pasted as values; the base case ties to the DCF sheet (check below).
A4: Driver | B4: Value at lower input ($) | C4: Value at higher input ($) | D4: Swing ($)
A5: WACC +/- 1.0 pt | B5: 134.4654 | C5: 87.088 | D5: 47.3774
A6: Beta +/- 0.2 | B6: 125.0381 | C6: 91.4344 | D6: 33.6037
A7: Terminal growth +/- 0.5 pt | B7: 95.7548 | C7: 117.7379 | D7: 21.9832
A8: EBIT margin +/- 1.0 pt | B8: 94.8541 | C8: 116.2166 | D8: 21.3625
A9: Capex % of revenue +/- 0.5 pt | B9: 112.6475 | C9: 98.4233 | D9: 14.2242
A10: Equity risk premium +/- 0.5 pt | B10: 112.1811 | C10: 99.657 | D10: 12.5241
A11: Year-1 revenue growth +/- 2.0 pts | B11: 99.8174 | C11: 111.5062 | D11: 11.6888
A12: Tax rate +/- 2.0 pts | B12: 108.7388 | C12: 102.332 | D12: 6.4067
A14: Base case (Python) | B14: 105.53538
A15: Base case (this workbook, DCF sheet) | B15: ='DCF'!$B$37
A16: Difference | B16: =B15-B14
A18: What would have to be true to justify the current share price
A19: (each input solved on its own, all others at base case)
A20: WACC | B20: 0.058837 | C20: base case: 7.03%
A21: EBIT margin | B21: 0.145057 | C21: base case: 11.26%
A22: Terminal growth | B22: 0.036808 | C22: base case: 2.50%
A23: Year-1 revenue growth (then fading) | B23: 0.171155 | C23: base case: 6.53%
